{
    "num_agents": 4,
    "num_tasks": 10,
    "num_obstacles": 0,
    "max_speed": 16,
    "max_deadline": 392.2960680247461,
    "map": {
        "width": 240,
        "height": 160
    },
    "tasks": [
        {
            "id": 0,
            "x": 173,
            "y": 60,
            "start_time": 0,
            "end_time": 392
        },
        {
            "id": 1,
            "x": 216,
            "y": 20,
            "start_time": 0,
            "end_time": 392
        },
        {
            "id": 2,
            "x": 217,
            "y": 20,
            "start_time": 0,
            "end_time": 392
        },
        {
            "id": 3,
            "x": 68,
            "y": 20,
            "start_time": 0,
            "end_time": 392
        },
        {
            "id": 4,
            "x": 60,
            "y": 40,
            "start_time": 0,
            "end_time": 392
        },
        {
            "id": 5,
            "x": 100,
            "y": 120,
            "start_time": 0,
            "end_time": 392
        },
        {
            "id": 6,
            "x": 224,
            "y": 60,
            "start_time": 0,
            "end_time": 392
        },
        {
            "id": 7,
            "x": 76,
            "y": 80,
            "start_time": 0,
            "end_time": 392
        },
        {
            "id": 8,
            "x": 199,
            "y": 120,
            "start_time": 0,
            "end_time": 392
        },
        {
            "id": 9,
            "x": 148,
            "y": 60,
            "start_time": 0,
            "end_time": 392
        }
    ],
    "agents": [
        {
            "id": 0,
            "x": 9,
            "y": 32.0,
            "speed": 15
        },
        {
            "id": 1,
            "x": 36,
            "y": 64.0,
            "speed": 15
        },
        {
            "id": 2,
            "x": 15,
            "y": 96.0,
            "speed": 15
        },
        {
            "id": 3,
            "x": 0,
            "y": 128.0,
            "speed": 15
        }
    ],
    "durations": [
        {
            "agent": 0,
            "task": 0,
            "duration": 11
        },
        {
            "agent": 0,
            "task": 1,
            "duration": 18
        },
        {
            "agent": 0,
            "task": 2,
            "duration": 14
        },
        {
            "agent": 0,
            "task": 3,
            "duration": 11
        },
        {
            "agent": 0,
            "task": 4,
            "duration": 13
        },
        {
            "agent": 0,
            "task": 5,
            "duration": 16
        },
        {
            "agent": 0,
            "task": 6,
            "duration": 15
        },
        {
            "agent": 0,
            "task": 7,
            "duration": 13
        },
        {
            "agent": 0,
            "task": 8,
            "duration": 19
        },
        {
            "agent": 0,
            "task": 9,
            "duration": 16
        },
        {
            "agent": 1,
            "task": 0,
            "duration": 19
        },
        {
            "agent": 1,
            "task": 1,
            "duration": 11
        },
        {
            "agent": 1,
            "task": 2,
            "duration": 19
        },
        {
            "agent": 1,
            "task": 3,
            "duration": 14
        },
        {
            "agent": 1,
            "task": 4,
            "duration": 12
        },
        {
            "agent": 1,
            "task": 5,
            "duration": 16
        },
        {
            "agent": 1,
            "task": 6,
            "duration": 17
        },
        {
            "agent": 1,
            "task": 7,
            "duration": 18
        },
        {
            "agent": 1,
            "task": 8,
            "duration": 18
        },
        {
            "agent": 1,
            "task": 9,
            "duration": 19
        },
        {
            "agent": 2,
            "task": 0,
            "duration": 12
        },
        {
            "agent": 2,
            "task": 1,
            "duration": 10
        },
        {
            "agent": 2,
            "task": 2,
            "duration": 16
        },
        {
            "agent": 2,
            "task": 3,
            "duration": 17
        },
        {
            "agent": 2,
            "task": 4,
            "duration": 18
        },
        {
            "agent": 2,
            "task": 5,
            "duration": 11
        },
        {
            "agent": 2,
            "task": 6,
            "duration": 17
        },
        {
            "agent": 2,
            "task": 7,
            "duration": 11
        },
        {
            "agent": 2,
            "task": 8,
            "duration": 14
        },
        {
            "agent": 2,
            "task": 9,
            "duration": 10
        },
        {
            "agent": 3,
            "task": 0,
            "duration": 18
        },
        {
            "agent": 3,
            "task": 1,
            "duration": 15
        },
        {
            "agent": 3,
            "task": 2,
            "duration": 14
        },
        {
            "agent": 3,
            "task": 3,
            "duration": 17
        },
        {
            "agent": 3,
            "task": 4,
            "duration": 18
        },
        {
            "agent": 3,
            "task": 5,
            "duration": 18
        },
        {
            "agent": 3,
            "task": 6,
            "duration": 12
        },
        {
            "agent": 3,
            "task": 7,
            "duration": 16
        },
        {
            "agent": 3,
            "task": 8,
            "duration": 12
        },
        {
            "agent": 3,
            "task": 9,
            "duration": 18
        }
    ],
    "wait_time": {},
    "obstacles": []
}